time_server/__init__.py
time_server/server.py
time_server_yamacr-0.1.3.dist-info/METADATA
time_server_yamacr-0.1.3.dist-info/WHEEL
time_server_yamacr-0.1.3.dist-info/entry_points.txt
time_server_yamacr-0.1.3.dist-info/top_level.txt
time_server_yamacr-0.1.3.dist-info/RECORD
