Metadata-Version: 2.1
Name: time-server-yamacr
Version: 0.1.3
Summary: A simple web server that returns the current time.
Home-page: https://github.com/rsmymc/cyb600_project1
Author: Rasim Yamac
Author-email: yamacr@canisius.edu
License: UNKNOWN
Platform: UNKNOWN
Classifier: Programming Language :: Python :: 3
Classifier: License :: OSI Approved :: MIT License
Classifier: Operating System :: OS Independent
Requires-Python: >=3.7
Requires-Dist: flask
